{
    "id":"c80c2a58-00b9-4098-a1c2-b8c0dbec268f",
    "lat": "13.8953037",
    "lng": "100.5175848",
    "city":"Nonthaburi",
    "name":"ร้านกัญชาใกล้ฉัน",
    "type":null,
    "business_images":[
      "512183095f5cfc137bbdf71c30e797f1",
      "1bac535e4543f7dad504f602a3e78efe",
      "1d7fa3979031056c7094fbb8255f86ac"
    ],
    "google_images":[
      "dd5bd90b49e28ff0e2f784f4ce65ea32",
      "5cab797016ee8894589df6aabe3e7569",
      "fc2738b642c56cba28eea57c67fb32d8"
    ],
    "status":"approved",
    "website":"https://lin.ee/3z7oELI",
    "phone":"+66 98 786 7678",
    "opening_hours":[
      {
        "open":{
          "day":0,
          "time":"1000"
        },
        "close":{
          "day":1,
          "time":"0200"
        }
      },
      {
        "open":{
          "day":1,
          "time":"1000"
        },
        "close":{
          "day":2,
          "time":"0200"
        }
      },
      {
        "open":{
          "day":2,
          "time":"1000"
        },
        "close":{
          "day":3,
          "time":"0200"
        }
      },
      {
        "open":{
          "day":3,
          "time":"1000"
        },
        "close":{
          "day":4,
          "time":"0200"
        }
      },
      {
        "open":{
          "day":4,
          "time":"1000"
        },
        "close":{
          "day":5,
          "time":"0200"
        }
      },
      {
        "open":{
          "day":5,
          "time":"1000"
        },
        "close":{
          "day":6,
          "time":"0200"
        }
      },
      {
        "open":{
          "day":6,
          "time":"1000"
        },
        "close":{
          "day":0,
          "time":"0200"
        }
      }
    ],
    "line":"https://lin.ee/3z7oELI",
    "google_url":"https://maps.google.com/?cid=13960321541747893044",
    "place_id":"PuVWP-RI5sJS5wNEABZqYabTipR",
    "facebook":"https://www.facebook.com/BASGAMER01?mibextid=LQQJ4d",
    "description":"จำหน่ายช่อดอก Mid-Grade Top shelf Exotic ราคามิตรภาพ รับประกันคุณภาพ💚",
    "products_flowers":[
      {
        "id":"c3c2342d-a0ff-42e3-b750-61d1b5c54bd7",
        "name":"Cake’n cream IN HOUSE",
        "description":"Cake N' Cream - Inhouse Genetics\nหรืออีกชื่อนึงก็คือ \nPancakes จาก Cookies\n\nโดยเป็นลูกผสมระหว่าง\nLondon Pound Cake#75 x Kush Mints 11\n\nกลิ่นเทอร์พีนจะออกไปทาง\nKush Mints และติด London Pound Cake มานิดหน่อย โดยรวมแล้ว กลิ่นคล้ายทางฝั่ง อิมพอร์ต จาก อเมริกา แต่กลิ่นตัวนี้แรงกว่า\nกลิ่นให้ 9.5/10 \nเอฟเฟคให้ 9/10\nรูปทรงให้ 8.5/10 \nบอกตรง ๆ เลยว่า แรงมาก 🔥",
        "images":[
          "238b2abbed69e2a312c827cf7f02218a"
        ],
        "thc":28,
        "cbd":0,
        "sativa":60,
        "indica":40,
        "images_coa":[
          
        ],
        "quality":"AAA",
        "disabled":false,
        "created_at":"2023-03-13T16:58:04.99902+00:00",
        "updated_at":"2023-04-15T23:00:05.292121+00:00"
      },
      {
        "id":"ee84da15-e07f-4b50-bb5b-3a656831a6e2",
        "name":"Dosidos BERNEY’S FRAM",
        "description":"Dos 33 มีเอฟเฟกต์ที่แข็งแกร่งซึ่งสร้างสมดุลระหว่างความ\nกระปรี้กระเปร่าทางจิตใจอันน่ารื่นรมย์กับเอฟเฟกต์ทาง\nร่างกายที่สะดวกสบาย หลังจากใช้ Dos Si Dos 33 คุณจะรู้สึกถึงประจุไฟฟ้าของพลังงานเป็นอย่างแรก ตามมาด้วยความรู้สึกสบายที่สงบ หลังจากความสนุกครั้งแรกเอฟเฟคโดยรวมจะจางหายไปเป็นความรู้สึกสงบที่ผ่อนคลายซึ่งเป็น\nเพียงการปลอบประโลมเล็กน้อย",
        "images":[
          "238b2abbed69e2a312c827cf7f02218a"
        ],
        "thc":0,
        "cbd":0,
        "sativa":40,
        "indica":60,
        "images_coa":[
          
        ],
        "quality":"AAA",
        "disabled":false,
        "created_at":"2023-03-13T17:04:05.798257+00:00",
        "updated_at":"2023-04-15T23:00:05.288572+00:00"
      },
      {
        "id":"1428369c-2133-4b91-bbf5-8e30b518f117",
        "name":"Sugur cane",
        "description":"Sugarcane มีกลิ่นหอมหวานเหมือนน้ำตาล และรสชาติก็คล้ายมมันอีกด้วย ควันของมันนั้นลื่นคอ ไม่แสบหรือแทงคอมาก เหมาะสำหรับมือใหม่ที่อยากจะลองของแรง สายพันธุ์นี้ยังได้รับความนิยมอย่างมากในกลุ่มผู้หญิงอีกด้วย มันทำให้คุณรู้สึกหัวตื้อ และรู้สึกหิวอยากกินขนม \n",
        "images":[
          "0adc185acbc539b3dc14ec5ef9754c9a"
        ],
        "thc":22,
        "cbd":0,
        "sativa":60,
        "indica":40,
        "images_coa":[
          
        ],
        "quality":"B",
        "disabled":false,
        "created_at":"2023-03-14T06:41:09.004541+00:00",
        "updated_at":"2023-04-15T23:00:05.29791+00:00"
      }
    ],
    "products_seeds":[
      
    ],
    "products_prerolls":[
      
    ],
    "products_edibles":[
      
    ],
    "products_topicals":[
      
    ],
    "products_gear":[
      
    ],
    "products_misc":[
      
    ],
    "reviews":[
      {
        "author":"Pong Satorn",
        "avatar":"c02de97175ceb227c14caec6d8027809",
        "content":"คุณภาพดี ราคาถูก การันตรีที่นี่ที่เดียวจบ เนื้อเมา ท่อมยัน😁🚀🚀\n\n(Translated by Google)\nGood quality, cheap price, guaranteed here in one place, finished, drunk meat, Tom Yan 😁🚀🚀",
        "review_date":"2023-03-15T10:50:22.954+00:00",
        "rating":5,
        "images":[
          
        ],
        "url":"https://www.google.com/maps/contrib/118262194415731787368?hl=en-US"
      }
    ],
    "reviews_aggregate":{
      "aggregate":{
        "sum":{
          "rating":5
        },
        "count":1
      }
    },
    "suggestions":[
      {
        "distance":0.833151009986404,
        "dispensary":{
          "id":"ab46943f-8a27-42f8-894d-fc9ae9f65969",
          "city":"Nonthaburi",
          "name":"ร้านขายกัญชา คุกกี้กัญชาไทย By ยิ้ม ยิ้ม บางตลาด",
          "types":[
            "Delivery",
            "Cafe"
          ],
          "lat":13.8913461,
          "lng":100.5112205,
          "reviews_aggregate":{
            "aggregate":{
              "sum":{
                "rating":20
              },
              "count":4
            }
          },
          "reviews_misc_real":{
            "aggregate":{
              "sum":{
                "rating":20
              },
              "count":4
            }
          },
          "image":"039af24a9a463d899c56e9c834a6b6b0",
          "has_products":false,
          "address":"199/147 Pak Kret District, Nonthaburi 11120, Thailand",
          "open":true
        }
      },
      {
        "distance":1.0438821985325042,
        "dispensary":{
          "id":"e377c6cc-6b05-4d8a-ad5d-0579aa367b4c",
          "city":"Nonthaburi",
          "name":"CLOUD9 weed store",
          "types":[
            
          ],
          "lat":13.8873199,
          "lng":100.5227734,
          "reviews_aggregate":{
            "aggregate":{
              "sum":{
                "rating":77
              },
              "count":16
            }
          },
          "reviews_misc_real":{
            "aggregate":{
              "sum":{
                "rating":77
              },
              "count":16
            }
          },
          "image":"8d14205b305451efdab69ac62877866d",
          "has_products":false,
          "address":"22/69 Soi Samakkhi 29, Tambon Bang Talat, Amphoe Pak Kret, Chang Wat Nonthaburi 11120, Thailand",
          "open":false
        }
      },
      {
        "distance":1.714229628150576,
        "dispensary":{
          "id":"5599f6b3-16b1-4b22-b12c-ac73a3771dd0",
          "city":"Nonthaburi",
          "name":"กาแฟ green happyness",
          "types":[
            
          ],
          "lat":13.8831979,
          "lng":100.5275329,
          "reviews_aggregate":{
            "aggregate":{
              "sum":{
                "rating":5
              },
              "count":1
            }
          },
          "reviews_misc_real":{
            "aggregate":{
              "sum":{
                "rating":5
              },
              "count":1
            }
          },
          "has_products":false,
          "address":"420 เมือง Nonthaburi 11000, Thailand",
          "open":false
        }
      },
      {
        "distance":1.783806479898139,
        "dispensary":{
          "id":"9a3f6fd7-1a9a-4468-bbc1-a428b5553b9e",
          "city":"Nonthaburi",
          "name":"Green happiness 420",
          "types":[
            
          ],
          "lat":13.8821905,
          "lng":100.5272132,
          "reviews_aggregate":{
            "aggregate":{
              "sum":{
                "rating":null
              },
              "count":0
            }
          },
          "reviews_misc_real":{
            "aggregate":{
              "sum":{
                "rating":null
              },
              "count":0
            }
          },
          "has_products":false,
          "address":"VGJG+VVG, Soi Samakkee 28, Tambon Tha Sai, Amphoe Mueang Nonthaburi, Chang Wat Nonthaburi 11000, Thailand",
          "open":false
        }
      },
      {
        "distance":2.3071770783848478,
        "dispensary":{
          "id":"a9e63cca-497d-4fbf-99ea-a01f050ffbfd",
          "city":"Nonthaburi",
          "name":"Da hong hua",
          "types":[
            "Wholesaler",
            "Cafe",
            "Grower",
            "Delivery"
          ],
          "lat":13.9112325,
          "lng":100.5314944,
          "reviews_aggregate":{
            "aggregate":{
              "sum":{
                "rating":10
              },
              "count":2
            }
          },
          "reviews_misc_real":{
            "aggregate":{
              "sum":{
                "rating":10
              },
              "count":2
            }
          },
          "image":"1ba5f7d50ee6e4187f63a6581ac21fac",
          "has_products":false,
          "address":"111 Tambon Bang Phut, Amphoe Pak Kret, Chang Wat Nonthaburi 11120, Thailand",
          "open":false
        }
      },
      {
        "distance":2.526643849137897,
        "dispensary":{
          "id":"c4a94207-86c0-4318-9d2a-a036fa072859",
          "city":"Nonthaburi",
          "name":"Mary Jane",
          "types":[
            
          ],
          "lat":13.8771438,
          "lng":100.5317666,
          "reviews_aggregate":{
            "aggregate":{
              "sum":{
                "rating":5
              },
              "count":1
            }
          },
          "reviews_misc_real":{
            "aggregate":{
              "sum":{
                "rating":5
              },
              "count":1
            }
          },
          "has_products":false,
          "address":"51 Pracha Niwet 3 Soi 11, Tambon Tha Sai, เมือง Chang Wat Nonthaburi 11000, Thailand",
          "open":false
        }
      },
      {
        "distance":2.604696634910468,
        "dispensary":{
          "id":"f9a5bbbc-e4dc-4efe-998f-ca501a0f6121",
          "city":"Nonthaburi",
          "name":"natural power",
          "types":[
            
          ],
          "lat":13.8723614,
          "lng":100.5224267,
          "reviews_aggregate":{
            "aggregate":{
              "sum":{
                "rating":null
              },
              "count":0
            }
          },
          "reviews_misc_real":{
            "aggregate":{
              "sum":{
                "rating":null
              },
              "count":0
            }
          },
          "has_products":false,
          "address":"150 ซอย ติวานนท์ 38 Mueang Nonthaburi District, Nonthaburi 11000, Thailand",
          "open":false
        }
      },
      {
        "distance":2.727146189945672,
        "dispensary":{
          "id":"8eadf5d7-70ad-4e16-a96e-65fa23705e4f",
          "city":"Nonthaburi",
          "name":"แมวยัน by Joss WëëD&Benz WëëD",
          "types":[
            
          ],
          "lat":13.8721859,
          "lng":100.5260752,
          "reviews_aggregate":{
            "aggregate":{
              "sum":{
                "rating":5
              },
              "count":1
            }
          },
          "reviews_misc_real":{
            "aggregate":{
              "sum":{
                "rating":null
              },
              "count":0
            }
          },
          "has_products":false,
          "address":"244 Tambon Tha Sai, Amphoe Mueang Nonthaburi, Chang Wat Nonthaburi 11000, Thailand",
          "open":false
        }
      },
      {
        "distance":2.7344608570349496,
        "dispensary":{
          "id":"35c3053b-158d-48b4-9593-e0677e6c7e3a",
          "city":"Nonthaburi",
          "name":"กัญชาเดลิเวอรี่",
          "types":[
            
          ],
          "lat":13.9077337,
          "lng":100.4958678,
          "reviews_aggregate":{
            "aggregate":{
              "sum":{
                "rating":20
              },
              "count":4
            }
          },
          "reviews_misc_real":{
            "aggregate":{
              "sum":{
                "rating":20
              },
              "count":4
            }
          },
          "image":"74baa4a3b2daac7a69c1615dbd8999b5",
          "has_products":false,
          "address":"23 Tambon Pak Kret, ปากเกร็ด Chang Wat Nonthaburi 11120, Thailand",
          "open":true
        }
      },
      {
        "distance":2.8862852257064797,
        "dispensary":{
          "id":"dc41b5d9-b159-400d-8dbf-c20166b28242",
          "city":"Nonthaburi",
          "name":"สหวรรณคลีนิก",
          "types":[
            
          ],
          "lat":13.8731661,
          "lng":100.5316468,
          "reviews_aggregate":{
            "aggregate":{
              "sum":{
                "rating":15
              },
              "count":3
            }
          },
          "reviews_misc_real":{
            "aggregate":{
              "sum":{
                "rating":5
              },
              "count":1
            }
          },
          "image":"c0838b6d2d05191297fce396ab5cedb0",
          "has_products":false,
          "address":"VGFJ+7M6, Ta Sai, Mueang Nonthaburi District, Nonthaburi 11000, Thailand",
          "open":false
        }
      },
      {
        "distance":2.887425303239612,
        "dispensary":{
          "id":"116668e5-1d62-43a9-8ac5-04026508e52a",
          "city":"Nonthaburi",
          "name":"87 Cannabis Shop",
          "types":[
            "Cafe",
            "Dispensary",
            "Farm"
          ],
          "lat":13.9034595,
          "lng":100.5431597,
          "reviews_aggregate":{
            "aggregate":{
              "sum":{
                "rating":10
              },
              "count":2
            }
          },
          "reviews_misc_real":{
            "aggregate":{
              "sum":{
                "rating":10
              },
              "count":2
            }
          },
          "image":"6e08ca70f7d626436505f2404a753496",
          "has_products":false,
          "address":"Soi Chaeng Watthana-Pakkret 39, Tambon Khlong Klua, Amphoe Pak Kret, Chang Wat Nonthaburi 11120, Thailand",
          "open":true
        }
      },
      {
        "distance":3.0633031480365798,
        "dispensary":{
          "id":"f8a2278a-c614-4fb8-b587-a21ac97d579f",
          "city":"Nonthaburi",
          "name":"บ้านเพื่อนกัญ420",
          "types":[
            
          ],
          "lat":13.9128698,
          "lng":100.539645,
          "reviews_aggregate":{
            "aggregate":{
              "sum":{
                "rating":15
              },
              "count":3
            }
          },
          "reviews_misc_real":{
            "aggregate":{
              "sum":{
                "rating":15
              },
              "count":3
            }
          },
          "image":"0cbd72ba306e382fe77fc8ca281f07d5",
          "has_products":false,
          "address":"Sukhothai Avenue 99 Tambon Bang Phut, Amphoe Pak Kret, Chang Wat Nonthaburi 11120, Thailand",
          "open":false
        }
      },
      {
        "distance":3.158318257067877,
        "dispensary":{
          "id":"5a3f2640-523f-42df-bed9-07f650cd55ad",
          "city":"Nonthaburi",
          "name":"UpperYard เมืองทองธานี",
          "types":[
            "Cafe",
            "Restaurant"
          ],
          "lat":13.9134516,
          "lng":100.5402917,
          "reviews_aggregate":{
            "aggregate":{
              "sum":{
                "rating":35
              },
              "count":7
            }
          },
          "reviews_misc_real":{
            "aggregate":{
              "sum":{
                "rating":35
              },
              "count":7
            }
          },
          "image":"4ce4d7818925f2ce6e71cb688479cecd",
          "has_products":true,
          "address":"3rd Floor 55/612 Soi B1 SukhothaiAve99 MuangThong Thani, Bangpud, อำเภอปากเกร็ด นนทบุรี 11120, Thailand",
          "open":false
        }
      },
      {
        "distance":3.3824306816032412,
        "dispensary":{
          "id":"7a626af7-f30f-4ffe-9668-19886f0823a2",
          "city":"Nonthaburi",
          "name":"Highlife Og",
          "types":[
            
          ],
          "lat":13.9163077,
          "lng":100.5404549,
          "reviews_aggregate":{
            "aggregate":{
              "sum":{
                "rating":5
              },
              "count":1
            }
          },
          "reviews_misc_real":{
            "aggregate":{
              "sum":{
                "rating":5
              },
              "count":1
            }
          },
          "image":"fe13515e1f6440fbb174bf5e6727a8ba",
          "has_products":false,
          "address":"ซอย เมืองทองธานี บ้านใหม่ Amphoe Pak Kret, Chang Wat Nonthaburi 11120, Thailand",
          "open":false
        }
      },
      {
        "distance":3.4840307473983674,
        "dispensary":{
          "id":"2cae200b-946e-47da-8e21-1bd4f3b63ec5",
          "city":"Nonthaburi",
          "name":"WEED HOUSE",
          "types":[
            
          ],
          "lat":13.8909189,
          "lng":100.5497036,
          "reviews_aggregate":{
            "aggregate":{
              "sum":{
                "rating":20
              },
              "count":4
            }
          },
          "reviews_misc_real":{
            "aggregate":{
              "sum":{
                "rating":20
              },
              "count":4
            }
          },
          "image":"2de331dbe4b2fca6defecdbf241195e0",
          "has_products":false,
          "address":"34/149 ชุมชน, 13 หมู่8 ซอย บางมดแลนด์ ตำบลบางตลาด อำเภอปากเกร็ด นนทบุรี 11120, Thailand",
          "open":false
        }
      }
    ]
  }